{"40": {"becameSuitTime": 1596992770.499, "savedBy": null, "track": "m", "numFloors": "5", "difficulty": "8", "state": "suit", "block": "40"}, "44": {"becameSuitTime": 1596992995.421, "savedBy": null, "track": "s", "numFloors": "0", "difficulty": "9", "state": "cogdo", "block": "44"}, "15": {"becameSuitTime": 1596992770.5, "savedBy": null, "track": "s", "numFloors": "1", "difficulty": "9", "state": "suit", "block": "15"}, "16": {"becameSuitTime": 1596993084.578, "savedBy": null, "track": "s", "numFloors": "0", "difficulty": "7", "state": "cogdo", "block": "16"}, "19": {"becameSuitTime": 1596992813.411, "savedBy": null, "track": "s", "numFloors": "5", "difficulty": "7", "state": "suit", "block": "19"}, "21": {"becameSuitTime": 1596992770.501, "savedBy": null, "track": "m", "numFloors": "5", "difficulty": "8", "state": "suit", "block": "21"}}